{"appStates":{"states":"Started,Initialized,LazyLoadStage,InCall,CallEnded,InCall,CallEnded","lastStateTime":1612158131.988},"criticalAppStates":{"states":"Started,Initialized,LazyLoadStage","lastStateTime":1612155044.697},"lastUsedProfileType":"AAD","webAppStates":{"states":"AuthstrapDomContentLoaded,AuthstrapJsLoaded,Unloaded,IndexInitialize,IndexAppCacheUpdateNotReady,IndexJsLoaded,IndexHtmlLoaded,Inactive,Interactive,InCall,Presenting,InCall,Offline,Disconnected,Interactive,InCall,Interactive,Inactive,LongInactive,Offline","lastStateTime":1612161334.158},"tenantModel":"","tenantRegion":"apac","userUpn":"1032180280@mitwpu.ac.in","cachedUpnDomain":"mitwpu.ac.in","cachedConfigService":"https://teams.microsoft.com","updatePolicy":{"allowManagedUpdates":false,"policyLastUpdated":1607481996510},"badLifecycleCount":3,"activityEvents":{"events":["desktop_web_console_error_log","panelview_postSignIn","app_launch_metadata","gpu-process-integrity-level","desktop_update_policy_load","desktop_update_policy_request","desktop_settings_save","desktop_webview_will_attach","desktop_er_add","register-experience-rend-with-store","plugin_host_init","attach-createstore-to-exp-webview","desktop_flash_taskbar_icon","desktop_spellcheckerservice_init","plugin_host_init_wait","module_require","calling_call_disconnected","calling_call_disconnected","calling_call_disconnected","desktop_webview_send_identity","module_require","calling_service_init","desktop_flash_taskbar_icon","desktop_flash_taskbar_icon","desktop_http_on_error","calling_call_disconnected","calling_call_disconnected","desktop_http_on_error","calling_call_disconnected","desktop_flash_taskbar_icon","desktop_flash_taskbar_icon","desktop_flash_taskbar_icon","desktop_settings_save"],"lastEventTime":1612160443171},"diagnosticEvents":{"diagnosticEvents":"ua:desktop_spellcheckerservice_init,ua:plugin_host_init_wait,ua:module_require,ua:calling_call_disconnected,ua:calling_call_disconnected,ua:calling_call_disconnected,ua:desktop_webview_send_identity,ua:module_require,ua:calling_service_init,ua:desktop_flash_taskbar_icon,ua:desktop_flash_taskbar_icon,wa:InCall,as:InCall,wa:Presenting,wa:InCall,ua:desktop_http_on_error,wa:Offline,as:CallEnded,wa:Disconnected,wa:Interactive,wa:InCall,as:InCall,ua:calling_call_disconnected,ua:calling_call_disconnected,ua:desktop_http_on_error,wa:Interactive,as:CallEnded,ua:calling_call_disconnected,wa:Inactive,ua:desktop_flash_taskbar_icon,ua:desktop_flash_taskbar_icon,wa:LongInactive,ua:desktop_flash_taskbar_icon,ua:desktop_settings_save,wa:Offline","diagnosticEventTime":"1612160443.171,1612161334.158"}}